whereabouts/AddressLoader.py
whereabouts/GNAFLoader.py
whereabouts/Matcher.py
whereabouts/MatcherPipeline.py
whereabouts/__init__.py
whereabouts/__main__.py
whereabouts/errors.py
whereabouts/utils.py
whereabouts/data_scripts/gnaf_tidy.py
whereabouts/db_utils/au_utils.py
whereabouts/models/__init__.py
whereabouts/models/db_test.db
whereabouts/queries/create_addrtext.sql
whereabouts/queries/create_geocoder_tables.sql
whereabouts/queries/create_indexes.sql
whereabouts/queries/create_indexes_skipphrase.sql
whereabouts/queries/create_phrases.sql
whereabouts/queries/create_skipphrases.sql
whereabouts/queries/create_trigram_index_step1.sql
whereabouts/queries/create_trigram_index_step2.sql
whereabouts/queries/create_trigram_index_step2b.sql
whereabouts/queries/create_trigram_index_step3.sql
whereabouts/queries/create_trigram_index_step4.sql
whereabouts/queries/create_trigramphrases.sql
whereabouts/queries/geocoder_query_skipphrase.sql
whereabouts/queries/geocoder_query_skipphrase2.sql
whereabouts/queries/geocoder_query_standard.sql
whereabouts/queries/geocoder_query_standard2.sql
whereabouts/queries/geocoder_query_standard3.sql
whereabouts/queries/geocoder_query_trigram.sql
whereabouts/queries/geocoder_query_trigramb.sql
whereabouts/queries/geocoder_query_trigramb2.sql
whereabouts/queries/geocoder_query_trigramb3.sql
whereabouts/queries/phrase_inverted.sql
whereabouts/queries/skipphrase_inverted.sql
whereabouts/queries/trigramphrase_inverted.sql
whereabouts-0.4.3.dist-info/METADATA
whereabouts-0.4.3.dist-info/WHEEL
whereabouts-0.4.3.dist-info/licenses/LICENSE
whereabouts-0.4.3.dist-info/RECORD
