Metadata-Version: 2.4
Name: whereabouts
Version: 0.4.3
Summary: Fast, accurate open source geocoding in Python
Project-URL: Source, https://github.com/ajl2718/whereabouts
Project-URL: Issues, https://github.com/ajl2718/whereabouts/issues
Project-URL: Documentation, https://whereabouts.readthedocs.io/en/latest
Author-email: Alex Lee <ajlee3141@gmail.com>
License: MIT License
License-File: LICENSE
Keywords: geocoding,geospatial,record linkage
Requires-Python: >=3.12
Requires-Dist: duckdb>=1.2.0
Requires-Dist: fastparquet>=2024.11.0
Requires-Dist: jinja2>=3.1.5
Requires-Dist: joblib>=1.4.2
Requires-Dist: lxml>=5.3.1
Requires-Dist: numpy==2.2.3
Requires-Dist: openpyxl>=3.1.5
Requires-Dist: pandas>=2.2.3
Requires-Dist: pyarrow>=19.0.1
Requires-Dist: pytest>=8.3.4
Requires-Dist: pyyaml>=6.0.2
Requires-Dist: requests==2.32.4
Requires-Dist: ruff>=0.9.7
Requires-Dist: scikit-learn>=1.6.1
Requires-Dist: scipy>=1.15.2
Requires-Dist: tqdm>=4.67.1
Requires-Dist: urllib3==2.6.0
